{
"type": "FeatureCollection",
"name": "f3_stop",
"crs": { "type": "name", "properties": { "name": "urn:ogc:def:crs:OGC:1.3:CRS84" } },
"features": [
{ "type": "Feature", "properties": { "id": 1 }, "geometry": { "type": "Point", "coordinates": [ 6.193410779769469, 46.19422751931284 ] } },
{ "type": "Feature", "properties": { "id": 2 }, "geometry": { "type": "Point", "coordinates": [ 6.170598097381816, 46.195197303243553 ] } }
]
}
